autograph_utils/__init__.py
autograph_utils/__main__.py
autograph_utils/main.py
autograph_utils-1.0.1.dist-info/LICENSE
autograph_utils-1.0.1.dist-info/METADATA
autograph_utils-1.0.1.dist-info/WHEEL
autograph_utils-1.0.1.dist-info/entry_points.txt
autograph_utils-1.0.1.dist-info/top_level.txt
autograph_utils-1.0.1.dist-info/RECORD
