Metadata-Version: 2.1
Name: autograph-utils
Version: 1.0.1
Summary: autograph-utils is a tool to configure a kinto server from an YAML file.
Author-email: Mozilla Services <dev-webdev@lists.mozilla.org>
License: Apache Software License 2.0
Project-URL: Repository, https://github.com/mozilla-services/autograph-utils
Keywords: autograph
Classifier: Programming Language :: Python
Classifier: Programming Language :: Python :: 3
Classifier: Intended Audience :: Developers
Classifier: License :: OSI Approved :: Apache Software License
Classifier: Natural Language :: English
License-File: LICENSE
Requires-Dist: Click >=7.0
Requires-Dist: aiohttp >=3.6
Requires-Dist: cryptography >=2.8
Requires-Dist: ecdsa >=0.13
Provides-Extra: dev
Requires-Dist: ruff ; extra == 'dev'
Requires-Dist: pytest ; extra == 'dev'
Requires-Dist: pytest-cache ; extra == 'dev'
Requires-Dist: pytest-aiohttp ; extra == 'dev'
Requires-Dist: pytest-cov ; extra == 'dev'
Requires-Dist: aioresponses ; extra == 'dev'
